setup.cfg
setup.py
pandoc_shortcaption/__init__.py
pandoc_shortcaption/__main__.py
pandoc_shortcaption.egg-info/PKG-INFO
pandoc_shortcaption.egg-info/SOURCES.txt
pandoc_shortcaption.egg-info/dependency_links.txt
pandoc_shortcaption.egg-info/entry_points.txt
pandoc_shortcaption.egg-info/requires.txt
pandoc_shortcaption.egg-info/top_level.txt